anchorscad_lib/utils/__init__.py
anchorscad_lib/utils/colours.py
anchorscad_lib/utils/openscad_finder.py
anchorscad_lib/utils/process_manager.py
anchorscad_utils-0.1.2.dist-info/METADATA
anchorscad_utils-0.1.2.dist-info/WHEEL
anchorscad_utils-0.1.2.dist-info/licenses/LICENSE
anchorscad_utils-0.1.2.dist-info/RECORD
