Metadata-Version: 2.4
Name: anchorscad-utils
Version: 0.1.2
Summary: Utility libraries for AnchorSCAD. Includes Colour, OpenSCAD finder, Process manager and more.
Project-URL: Homepage, https://github.com/owebeeone/anchorscad-utils
Project-URL: Bug Tracker, https://github.com/owebeeone/anchorscad-utils/issues
Author-email: Gianni Mariani <gianni@mariani.ws>
License-File: LICENSE
Classifier: License :: OSI Approved :: GNU Lesser General Public License v2 or later (LGPLv2+)
Classifier: Operating System :: OS Independent
Classifier: Programming Language :: Python :: 3
Requires-Python: >=3.10
Requires-Dist: anchorscad-test-tools
Requires-Dist: numpy
